rich_gradient/__init__.py
rich_gradient/_animated_gradient.py
rich_gradient/_base_gradient.py
rich_gradient/_logger.py
rich_gradient/cli.py
rich_gradient/default_styles.py
rich_gradient/gradient.py
rich_gradient/py.typed
rich_gradient/rule.py
rich_gradient/spectrum.py
rich_gradient/text.py
rich_gradient/theme.py
rich_gradient-0.3.6.dist-info/METADATA
rich_gradient-0.3.6.dist-info/WHEEL
rich_gradient-0.3.6.dist-info/entry_points.txt
rich_gradient-0.3.6.dist-info/licenses/LICENSE
rich_gradient-0.3.6.dist-info/RECORD
