Metadata-Version: 2.4
Name: rich-gradient
Version: 0.3.6
Summary: A gradient generator for the Rich library.
Author-email: Max Ludden <dev@maxludden.com>
License-File: LICENSE
Requires-Python: >=3.10
Requires-Dist: click<9.0.0,>=8.1.7
Requires-Dist: loguru>=0.7.3
Requires-Dist: rich-color-ext>=0.1.4
Requires-Dist: rich>=14.0.0
Requires-Dist: typer<0.13,>=0.12.5
